LICENSE
MANIFEST.in
README.md
setup.cfg
setup.py
glade/pbook.glade
glade/pbook.gladep
icons/back.png
icons/config.png
icons/forward.png
icons/green.png
icons/kill.png
icons/orange.png
icons/pandamon.png
icons/red.png
icons/retry.png
icons/savannah.png
icons/sync.png
icons/update.png
icons/yellow.png
panda_client.egg-info/PKG-INFO
panda_client.egg-info/SOURCES.txt
panda_client.egg-info/dependency_links.txt
panda_client.egg-info/requires.txt
panda_client.egg-info/top_level.txt
pandaclient/AthenaUtils.py
pandaclient/BookConfig.py
pandaclient/BookGUI.py
pandaclient/Client.py
pandaclient/FileSpec.py
pandaclient/Group_argparse.py
pandaclient/JobSpec.py
pandaclient/LocalJobSpec.py
pandaclient/LocalJobsetSpec.py
pandaclient/MiscUtils.py
pandaclient/MyproxyUtils.py
pandaclient/PBookCore.py
pandaclient/PBookScript.py
pandaclient/PLogger.py
pandaclient/PandaToolsPkgInfo.py
pandaclient/ParseJobXML.py
pandaclient/PathenaScript.py
pandaclient/PchainScript.py
pandaclient/PcontainerScript.py
pandaclient/PdbUtils.py
pandaclient/PhpoScript.py
pandaclient/PrunScript.py
pandaclient/PsubUtils.py
pandaclient/__init__.py
pandaclient/example_task.py
pandaclient/idds_api.py
pandaclient/localSpecs.py
pandaclient/openidc_utils.py
pandaclient/panda_api.py
pandaclient/panda_gui.py
pandaclient/panda_jupyter.py
pandaclient/pcontainer_core.py
pandaclient/queryPandaMonUtils.py
pandaclient/test_client_file.py
pandaclient/test_client_job.py
pandaclient/test_client_misc.py
pandaclient/test_client_submit_job.py
pandaclient/test_client_task.py
pandaclient/time_utils.py
scripts/pathena
scripts/pbook
scripts/pchain
scripts/pcontainer
scripts/phpo
scripts/prun
share/ConfigExtractor.py
share/FakeAppMgr.py
share/functions.sh
templates/conda_meta.yaml.template
templates/panda_setup.csh.template
templates/panda_setup.example.cfg.template
templates/panda_setup.sh.template
templates/site_path.sh.template